betterprint.py
betterprint-0.2.dist-info/DESCRIPTION.rst
betterprint-0.2.dist-info/METADATA
betterprint-0.2.dist-info/RECORD
betterprint-0.2.dist-info/WHEEL
betterprint-0.2.dist-info/metadata.json
betterprint-0.2.dist-info/top_level.txt
