Metadata-Version: 2.0
Name: betterprint
Version: 0.2
Summary: Alternate to pprint
Home-page: http://misc.slowchop.com/misc/wiki/BetterPrint
Author: Gerald Kaszuba
Author-email: gerald@geraldkaszuba.com
License: UNKNOWN
Download-URL: http://slowchop.com/betterprint/betterprint-0.1.tar.gz
Platform: UNKNOWN
